cli.py
besalu_notifier-0.1.1.dist-info/LICENSE
besalu_notifier-0.1.1.dist-info/METADATA
besalu_notifier-0.1.1.dist-info/WHEEL
besalu_notifier-0.1.1.dist-info/entry_points.txt
besalu_notifier-0.1.1.dist-info/top_level.txt
besalu_notifier-0.1.1.dist-info/RECORD
