Metadata-Version: 2.1
Name: besalu-notifier
Version: 0.1.1
Summary: A tool to watch the inventory of Cafe Besalu in Seattle, WA.
Home-page: https://github.com/aschokking/besalu-notifier
Author: Alex Schokking
Author-email: aschokking@gmail.com
License: MIT
Platform: UNKNOWN
Classifier: Programming Language :: Python :: 3
Classifier: License :: OSI Approved :: MIT License
Classifier: Operating System :: OS Independent
Requires-Dist: Click
Requires-Dist: notify-run
